nv200/__init__.py
nv200/_internal/_reentrant_lock.py
nv200/analysis.py
nv200/connection_utils.py
nv200/data_recorder.py
nv200/device_base.py
nv200/device_discovery.py
nv200/device_factory.py
nv200/doctest.py
nv200/eth_utils.py
nv200/generate_sync_module.py
nv200/lantronix_xport.py
nv200/main.py
nv200/nv200_device.py
nv200/serial_protocol.py
nv200/shared_types.py
nv200/spibox_device.py
nv200/syncwrap.py
nv200/telnet_protocol.py
nv200/transport_factory.py
nv200/transport_protocol.py
nv200/utils.py
nv200/waveform_generator.py
nv200-1.6.0.dist-info/METADATA
nv200-1.6.0.dist-info/WHEEL
nv200-1.6.0.dist-info/RECORD
