Metadata-Version: 2.4
Name: nv200
Version: 1.6.0
Summary: Python library for piezosystem NV200 device
Author: piezosystem jena GmbH
Requires-Python: >=3.12,<3.14
Classifier: Development Status :: 5 - Production/Stable
Classifier: Intended Audience :: Developers
Classifier: Operating System :: OS Independent
Classifier: Programming Language :: Python :: 3
Classifier: Programming Language :: Python :: 3.12
Classifier: Programming Language :: Python :: 3.13
Requires-Dist: aioserial (>=1.3.1,<2.0.0)
Requires-Dist: psutil (>=7.0.0,<8.0.0)
Requires-Dist: scipy (>=1.16.0,<2.0.0)
Requires-Dist: telnetlib3 (>=2.0.4,<3.0.0)
Project-URL: Bug Tracker, https://github.com/piezosystemjena/nv200-python-lib/issues
Project-URL: Documentation, https://piezosystemjena.github.io/nv200-python-lib/
Project-URL: Homepage, https://github.com/piezosystemjena/nv200-python-lib
Project-URL: Source, https://github.com/piezosystemjena/nv200-python-lib
